[
  {
    "id": 1,
    "id_komodity": 1,
    "komodity": {
      "id": 1,
      "id_jenis": 1,
      "jenis": {
        "id": 1,
        "name": "Pangan",
        "createdAt": "2025-05-01T10:00:00Z",
        "updatedAt": "2025-05-01T10:00:00Z",
        "komoditas": []
      },
      "nama": "Beras Premium",
      "deskripsi": "Beras kualitas tinggi",
      "foto": "/images/beras.jpg",
      "satuan": "kg",
      "jumlah": 200,
      "createdAt": "2025-05-01T10:00:00Z",
      "updatedAt": "2025-05-01T10:00:00Z"
    },
    "ukuran": "5kg",
    "jumlah_terjual": 10,
    "kualitas": "Premium",
    "id_produksi": 1,
    "produksi": {
      "id": 1,
      "id_asal": 1,
      "kode_produksi": "PROD001",
      "asal_produksi": {
        "id": 1,
        "nama": "Jawa Tengah",
        "createdAt": "2025-05-01T10:00:00Z",
        "updatedAt": "2025-05-01T10:00:00Z"
      },
      "createdAt": "2025-05-01T10:00:00Z",
      "updatedAt": "2025-05-01T10:00:00Z"
    },
    "keterangan": "Penjualan ke distributor",
    "createdAt": "2025-05-03T10:00:00Z",
    "updatedAt": "2025-05-03T10:00:00Z"
  }
]